ipy_pdcache/__init__.py
ipy_pdcache/main.py
ipy_pdcache-0.1.0.dist-info/WHEEL
ipy_pdcache-0.1.0.dist-info/METADATA
ipy_pdcache-0.1.0.dist-info/RECORD
