Metadata-Version: 2.1
Name: ipy-pdcache
Version: 0.1.0
Summary: Automatically cache results of intensive computations in IPython.
Home-page: https://github.com/kpj/ipy_pdcache
License: MIT
Author: kpj
Author-email: kim.philipp.jablonski@gmail.com
Requires-Python: >=3.7.1,<4.0.0
Classifier: License :: OSI Approved :: MIT License
Classifier: Programming Language :: Python :: 3
Classifier: Programming Language :: Python :: 3.8
Classifier: Programming Language :: Python :: 3.9
Requires-Dist: ipython (>=7.26.0,<8.0.0)
Requires-Dist: pandas (>=1.3.2,<2.0.0)
Project-URL: Repository, https://github.com/kpj/ipy_pdcache
